dkany/__about__.py
dkany/__init__.py
dkany/dataset.py
dkany/py.typed
dkany/utils.py
dkany/client/__init__.py
dkany/client/client.py
dkany/client/errors.py
dkany/data_hosts/__init__.py
dkany/data_hosts/sftp.py
dkany/luigi/__init__.py
dkany/luigi/luigi_utils.py
dkany-0.1.3.dist-info/METADATA
dkany-0.1.3.dist-info/WHEEL
dkany-0.1.3.dist-info/RECORD
