Metadata-Version: 2.4
Name: dkany
Version: 0.1.3
Summary: A wrapper library around the DKAN API
Author-email: Peter Mariani <pmariani@mathematica-mpr.com>, Drew McArthur <dmcarthur@mathematica-mpr.com>, Tom Coile <tcoile@mathematica-mpr.com>
License-Expression: MIT
Requires-Python: >=3.9
Requires-Dist: luigi>=3.6.0
Requires-Dist: paramiko>=4.0.0
Requires-Dist: pyyaml>=6.0.3
Requires-Dist: requests-toolbelt>=1.0.0
Requires-Dist: requests>=2.32.5
